palgen/__init__.py
palgen/__main__.py
palgen/interface.py
palgen/palgen.py
palgen/py.typed
palgen/application/__init__.py
palgen/application/log.py
palgen/application/runner.py
palgen/application/util.py
palgen/application/commands/__init__.py
palgen/application/commands/info.py
palgen/application/commands/manifest.py
palgen/ingest/__init__.py
palgen/ingest/filter.py
palgen/ingest/loader.py
palgen/ingest/path.py
palgen/ingest/transform.py
palgen/integrations/__init__.py
palgen/integrations/cmake/__init__.py
palgen/integrations/cmake/cli.py
palgen/integrations/cmake/palgen.cmake
palgen/integrations/conan/__init__.py
palgen/integrations/conan/cli.py
palgen/integrations/conan/generator.py
palgen/integrations/conan/palgen.py
palgen/loaders/__init__.py
palgen/loaders/ast_helper.py
palgen/loaders/builtin.py
palgen/loaders/loader.py
palgen/loaders/manifest.py
palgen/loaders/python.py
palgen/machinery/__init__.py
palgen/machinery/attributes.py
palgen/machinery/filesystem.py
palgen/machinery/pipeline.py
palgen/machinery/template.py
palgen/machinery/types.py
palgen/schemas/__init__.py
palgen/schemas/palgen.py
palgen/schemas/project.py
palgen/schemas/root.py
palgen/template/__init__.py
palgen/template/jinja.py
palgen/template/string.py
palgen-0.1.dist-info/LICENSE
palgen-0.1.dist-info/METADATA
palgen-0.1.dist-info/WHEEL
palgen-0.1.dist-info/entry_points.txt
palgen-0.1.dist-info/top_level.txt
palgen-0.1.dist-info/RECORD
