Metadata-Version: 2.1
Name: palgen
Version: 0.1
Summary: Code generation utility
Home-page: https://github.com/palliate/palgen
Author: Tsche
Author-email: contact@palliate.io
License: MIT
Project-URL: Bug Tracker, https://github.com/palliate/palgen/issues
Platform: unix
Platform: linux
Platform: osx
Platform: cygwin
Platform: win32
Classifier: Programming Language :: Python :: 3
Classifier: Programming Language :: Python :: 3 :: Only
Classifier: License :: OSI Approved :: MIT License
Classifier: Operating System :: OS Independent
Requires-Python: >=3.10
License-File: LICENSE
Requires-Dist: colorama ~=0.4.6
Requires-Dist: click ~=8.1.7
Requires-Dist: pydantic ~=2.1.1
Requires-Dist: pathspec ~=0.11.2
Requires-Dist: toml ~=0.10.2
Provides-Extra: conan
Requires-Dist: conan ~=2.0.9 ; extra == 'conan'
Provides-Extra: jinja2
Requires-Dist: jinja2 ~=3.1.2 ; extra == 'jinja2'
Provides-Extra: testing
Requires-Dist: pytest >=7.1.3 ; extra == 'testing'
Requires-Dist: pytest-cov >=4.0.0 ; extra == 'testing'
Requires-Dist: pytest-mock >=3.11.0 ; extra == 'testing'
Requires-Dist: mypy >=0.982 ; extra == 'testing'
Requires-Dist: pylint >=2.17.0 ; extra == 'testing'
Requires-Dist: types-toml ; extra == 'testing'
Requires-Dist: build ; extra == 'testing'
